anonymizer_data/__init__.py
anonymizer_data/anonymizer_data.py
anonymizer_data/cli.py
anonymizer_data/mask_dispatch.py
anonymizer_data/utils.py
anonymizer_data-0.1.1.dist-info/METADATA
anonymizer_data-0.1.1.dist-info/WHEEL
anonymizer_data-0.1.1.dist-info/entry_points.txt
anonymizer_data-0.1.1.dist-info/licenses/LICENSE
anonymizer_data-0.1.1.dist-info/RECORD
