Metadata-Version: 2.3
Name: anonymizer-data
Version: 0.1.1
Summary: The Anonymize library provides functionality to anonymize sensitive data in different formats, such as strings, lists, and dictionaries. This library is useful for developers who need to ensure data privacy in their applications.
Project-URL: Documentation, https://anonymize.readthedocs.io/en/latest/
Project-URL: Github, https://github.com/JhonatanRian/anonymize
Project-URL: Issues, https://github.com/JhonatanRian/anonymize/issues
Author-email: Jhonatan Rian <jhonatanrian@zohomail.com>
License-Expression: MIT
License-File: LICENSE
Classifier: Operating System :: OS Independent
Classifier: Programming Language :: Python :: 3.12
Classifier: Topic :: Internet
Classifier: Topic :: Software Development
Classifier: Topic :: Software Development :: Libraries
Classifier: Topic :: System :: Logging
Classifier: Topic :: Text Processing
Classifier: Topic :: Utilities
Requires-Python: >=3.12
Requires-Dist: rich>=13.9.2
Requires-Dist: typer>=0.12.5
Requires-Dist: validate-docbr>=1.10.0
